trivial_remote_semaphore/__init__.py
trivial_remote_semaphore/client.py
trivial_remote_semaphore/server.py
trivial_remote_semaphore-1.2.dist-info/DESCRIPTION.rst
trivial_remote_semaphore-1.2.dist-info/METADATA
trivial_remote_semaphore-1.2.dist-info/RECORD
trivial_remote_semaphore-1.2.dist-info/WHEEL
trivial_remote_semaphore-1.2.dist-info/entry_points.txt
trivial_remote_semaphore-1.2.dist-info/metadata.json
trivial_remote_semaphore-1.2.dist-info/top_level.txt
