Metadata-Version: 2.0
Name: trivial-remote-semaphore
Version: 1.2
Summary: Trivial Remote Semaphore (client & server)
Home-page: https://bitbucket.org/gclinch/trivial-remote-semaphore
Author: Graham Clinch
Author-email: g.clinch@lancaster.ac.uk
License: Apache License, Version 2.0
Platform: UNKNOWN
Classifier: Development Status :: 5 - Production/Stable
Classifier: License :: OSI Approved :: Apache Software License
Classifier: Topic :: System :: Distributed Computing
Requires-Dist: pyzmq
